[
  {
    "user_id": "f7f1c47a",
    "question_id": 2,
    "response_id": 1,
    "question_text": "*\"Can you describe a complex technical challenge you encountered in a past project, and walk us through your approach to troubleshooting and resolving it?\"*?",
    "timestamp": "20250815_040556",
    "filename": "user_f7f1c47a_q2_r1_20250815_040556.wav",
    "file_path": "recordings\\user_f7f1c47a_q2_r1_20250815_040556.wav"
  },
  {
    "user_id": "f7f1c47a",
    "question_id": 2,
    "response_id": 1,
    "question_text": "*\"Can you describe a complex technical challenge you encountered in a past project, and walk us through your approach to troubleshooting and resolving it?\"*?",
    "timestamp": "20250815_040613",
    "filename": "user_f7f1c47a_q2_r1_20250815_040613.wav",
    "file_path": "recordings\\user_f7f1c47a_q2_r1_20250815_040613.wav"
  }
]